Metadata-Version: 2.1
Name: email-sender-verifier
Version: 2.1.1
Summary: Email Verifier is a python library designed for sending One-Time-Passwords (OTP) and performing code verification via email.
Home-page: https://github.com/christiangarcia0311/email-sender-verifier
Author: Christian Garcia
Author-email: iyaniyan03112003@gmail.com
License: MIT
Classifier: Programming Language :: Python :: 3
Classifier: License :: OSI Approved :: MIT License
Classifier: Operating System :: OS Independent
Classifier: Topic :: Software Development :: Libraries :: Python Modules
License-File: LICENSE
